confidential_router/__init__.py
confidential_router/client.py
confidential_router/config.py
confidential_router/main.py
confidential_router/api/__init__.py
confidential_router/api/attest_router.py
confidential_router/api/chat_router.py
confidential_router/api/crypto_router.py
confidential_router/api/image_router.py
confidential_router/crypto/envelope.py
confidential_router/crypto/jwk.py
confidential_router/crypto/rsa_ops.py
confidential_router/models/__init__.py
confidential_router/models/schemas.py
confidential_router/provider/utils.py
confidential_router/provider/chat/__init__.py
confidential_router/provider/chat/openai.py
confidential_router/provider/image/__init__.py
confidential_router/provider/image/fal.py
confidential_router/services/key_cache.py
confidential_router/services/sidecar.py
confidential_router/utils/__init__.py
confidential_router/utils/base64utils.py
confidential_router-0.1.0.dist-info/METADATA
confidential_router-0.1.0.dist-info/WHEEL
confidential_router-0.1.0.dist-info/entry_points.txt
confidential_router-0.1.0.dist-info/top_level.txt
confidential_router-0.1.0.dist-info/RECORD
