Metadata-Version: 2.4
Name: confidential-router
Version: 0.1.0
Summary: Add your description here
Requires-Python: >=3.11
Requires-Dist: anthropic>=0.67.0
Requires-Dist: click>=8.0.0
Requires-Dist: cryptography>=45.0.7
Requires-Dist: dotenv>=0.9.9
Requires-Dist: fal>=1.39.2
Requires-Dist: fal-client>=0.7.0
Requires-Dist: fastapi>=0.116.1
Requires-Dist: google-genai>=1.37.0
Requires-Dist: jwt>=1.4.0
Requires-Dist: openai>=1.107.2
Requires-Dist: pyjwt>=2.10.1
Requires-Dist: requests>=2.32.5
Requires-Dist: ruff>=0.13.0
Requires-Dist: uvicorn>=0.35.0
